{
  "title": "Hands-On Lab: Eventual consistency in Big Data And Databases",
  "topic": "NoSQL Databases: CAP Theorem and BASE Transaction Model",
  "difficulty": "easy",
  "estimated_time": 30,
  "sections": [
    {
      "concept": "Eventual consistency",
      "title": "Exploring Eventual consistency",
      "difficulty": "easy",
      "scaffolding_level": "medium",
      "exercises": [
        {
          "type": "guided",
          "hints": 3,
          "description": "Implement a basic example demonstrating Eventual consistency",
          "starter_code": "# TODO: Implement Eventual consistency\n# Your code here\n",
          "solution": "# Solution for Eventual consistency\n# Implementation details\n",
          "test_cases": [
            {
              "input": "test_input",
              "expected": "expected_output"
            }
          ]
        }
      ],
      "learning_objectives": [
        "Understand the fundamentals of Eventual consistency",
        "Apply Eventual consistency in practical scenarios",
        "Implement solutions using Eventual consistency"
      ],
      "background": "Subsequent access operations temporarily can fail to read the updated data, but after a period, the updated data must eventually be read."
    }
  ],
  "prerequisites": [
    "Basic programming knowledge",
    "Understanding of databases"
  ],
  "technologies": [
    "Python",
    "Jupyter Notebook"
  ],
  "personalization_context": "big data and databases"
}