{
  "lab": {
    "title": "Hands-On Lab: TaskTracker in Big Data And Databases",
    "topic": "Batch Processing with MapReduce",
    "difficulty": "hard",
    "estimated_time": 60,
    "sections": [
      {
        "concept": "TaskTracker",
        "title": "Exploring TaskTracker",
        "difficulty": "hard",
        "scaffolding_level": "medium",
        "exercises": [
          {
            "type": "guided",
            "hints": 2,
            "description": "Implement a basic example demonstrating TaskTracker",
            "starter_code": "# TODO: Implement TaskTracker\n# Your code here\n",
            "solution": "# Solution for TaskTracker\n# Implementation details\n",
            "test_cases": [
              {
                "input": "test_input",
                "expected": "expected_output"
              }
            ]
          },
          {
            "type": "challenge",
            "hints": 1,
            "description": "Apply TaskTracker to solve a real-world problem",
            "starter_code": "# Challenge: Advanced TaskTracker\n",
            "solution": "# Advanced solution\n",
            "test_cases": []
          }
        ],
        "learning_objectives": [
          "Understand the fundamentals of TaskTracker",
          "Apply TaskTracker in practical scenarios",
          "Implement solutions using TaskTracker"
        ],
        "background": "will periodically report the usage of resources on the node and the progress of the task to the JobTracker through the \"heartbeat\", and at the same time receive the commands sent by the JobTracker and perform the corresponding operations (such as starting new tasks, killing tasks, etc.)"
      }
    ],
    "prerequisites": [
      "Basic programming knowledge",
      "Understanding of databases"
    ],
    "technologies": [
      "Python",
      "Jupyter Notebook"
    ],
    "personalization_context": "big data and databases"
  },
  "metadata": {
    "concept_name": "TaskTracker",
    "concept_definition": "will periodically report the usage of resources on the node and the progress of the task to the JobTracker through the \"heartbeat\", and at the same time receive the commands sent by the JobTracker and perform the corresponding operations (such as starting new tasks, killing tasks, etc.)",
    "source_topic": "Batch Processing with MapReduce",
    "model_used": "template",
    "personalization_applied": true
  },
  "success": true
}